mcp_server_cloudsearch/__init__.py
mcp_server_cloudsearch/client.py
mcp_server_cloudsearch/server.py
mcp_server_cloudsearch/tools/__init__.py
mcp_server_cloudsearch/tools/instance_info.py
mcp_server_cloudsearch/tools/resource_info.py
cloudsearch_mcp_server-0.1.1.dist-info/METADATA
cloudsearch_mcp_server-0.1.1.dist-info/WHEEL
cloudsearch_mcp_server-0.1.1.dist-info/entry_points.txt
cloudsearch_mcp_server-0.1.1.dist-info/top_level.txt
cloudsearch_mcp_server-0.1.1.dist-info/RECORD
